vismatrix/__init__.py
vismatrix/vismatrix.py
vismatrix-0.5.1.dist-info/METADATA
vismatrix-0.5.1.dist-info/WHEEL
vismatrix-0.5.1.dist-info/top_level.txt
vismatrix-0.5.1.dist-info/RECORD
