Metadata-Version: 2.1
Name: vismatrix
Version: 0.5.1
Summary: Output matrix or table in beautiful form
Home-page: https://github.com/VolodyaHoi/vismatrix
Author: VolodyaHoi
Author-email: i4masyrov@gmail.com
Requires-Dist: multipledispatch
